rocqblueprint/__init__.py
rocqblueprint/client.py
rocqblueprint/Packages/__init__.py
rocqblueprint/Packages/blueprint.py
rocqblueprint/Packages/renderer_templates/blueprint.jinja2s
rocqblueprint/jekyll_templates/404.html
rocqblueprint/jekyll_templates/Gemfile
rocqblueprint/jekyll_templates/Gemfile.lock
rocqblueprint/jekyll_templates/_config.yml
rocqblueprint/jekyll_templates/index.md
rocqblueprint/jekyll_templates/_include/mathjax.html
rocqblueprint/jekyll_templates/_layouts/default.html
rocqblueprint/jekyll_templates/assets/css/style.scss
rocqblueprint/static/blueprint.css
rocqblueprint/templates/blueprint.sty
rocqblueprint/templates/blueprint.yml
rocqblueprint/templates/content.tex
rocqblueprint/templates/extra_styles.css
rocqblueprint/templates/latexmkrc
rocqblueprint/templates/plastex.cfg
rocqblueprint/templates/print.tex
rocqblueprint/templates/web.tex
rocqblueprint/templates/macros/common.tex
rocqblueprint/templates/macros/print.tex
rocqblueprint/templates/macros/web.tex
rocqblueprint-0.0.9.dist-info/licenses/LICENSE
rocqblueprint-0.0.9.dist-info/licenses/NOTICE
rocqblueprint-0.0.9.dist-info/METADATA
rocqblueprint-0.0.9.dist-info/WHEEL
rocqblueprint-0.0.9.dist-info/entry_points.txt
rocqblueprint-0.0.9.dist-info/top_level.txt
rocqblueprint-0.0.9.dist-info/RECORD
