Metadata-Version: 2.4
Name: rocqblueprint
Version: 0.0.9
Summary: Rocq prover blueprint plasTeX plugin.
Author: Patrick Massot, Peter LeFanu Lumsdaine, Andrej Bauer, Reinis Cirpons
Maintainer-email: Reinis Cirpons <reinis.cirpons@inria.fr>
License-Expression: Apache-2.0
Project-URL: Homepage, https://github.com/reiniscirpons/rocqblueprint
Keywords: Rocq,Rocq blueprint
Classifier: Development Status :: 3 - Alpha
Classifier: Programming Language :: Python :: 3
Classifier: Operating System :: OS Independent
Requires-Python: >=3.8
License-File: LICENSE
License-File: NOTICE
Requires-Dist: plasTeX>=3.1
Requires-Dist: plastexshowmore>=0.0.2
Requires-Dist: plastexdepgraph>=0.0.4
Requires-Dist: click
Requires-Dist: rich
Requires-Dist: rich-click
Requires-Dist: tomlkit
Requires-Dist: Jinja2>=3.1.0
Requires-Dist: GitPython>=3.1.28
Dynamic: license-file
